trialflow_agro/__init__.py
trialflow_agro/pipeline.py
trialflow_agro-0.1.1.dist-info/licenses/LICENSE
trialflow_agro-0.1.1.dist-info/METADATA
trialflow_agro-0.1.1.dist-info/WHEEL
trialflow_agro-0.1.1.dist-info/entry_points.txt
trialflow_agro-0.1.1.dist-info/top_level.txt
trialflow_agro-0.1.1.dist-info/RECORD
