Metadata-Version: 2.4
Name: trialflow-agro
Version: 0.1.1
Summary: A lightweight, reproducible workflow template for analyzing on-farm agricultural trials.
Author: Gnaneswara (Akhil) Marupilla
License: MIT
Project-URL: Homepage, https://github.com/gmarupilla/trialflow-agro
Project-URL: Bug Tracker, https://github.com/gmarupilla/trialflow-agro/issues
Keywords: geospatial,agriculture,raster,climate,workflow
Requires-Python: >=3.9
License-File: LICENSE
Requires-Dist: numpy
Requires-Dist: pandas
Requires-Dist: geopandas
Requires-Dist: pyyaml
Requires-Dist: pydantic>=2.0
Requires-Dist: typer[all]
Requires-Dist: pymc>=5
Requires-Dist: arviz>=0.17
Requires-Dist: jinja2
Provides-Extra: dev
Requires-Dist: pytest; extra == "dev"
Requires-Dist: pytest-cov; extra == "dev"
Requires-Dist: ruff; extra == "dev"
Requires-Dist: black; extra == "dev"
Dynamic: license-file
